appveyor_client/__init__.py
appveyor_client/client.py
appveyor_client-0.1.0.dist-info/DESCRIPTION.rst
appveyor_client-0.1.0.dist-info/METADATA
appveyor_client-0.1.0.dist-info/RECORD
appveyor_client-0.1.0.dist-info/WHEEL
appveyor_client-0.1.0.dist-info/metadata.json
appveyor_client-0.1.0.dist-info/top_level.txt
