Metadata-Version: 2.0
Name: appveyor-client
Version: 0.1.0
Summary: Appveyor Python Client
Home-page: https://github.com/goanpeca/appveyor-client
Author: Gonzalo Pena-Castellanos
Author-email: goanpeca@gmail.com
License: MIT
Keywords: appveyor client continuous integration api rest ci
Platform: UNKNOWN
Classifier: Development Status :: 4 - Beta
Classifier: Intended Audience :: Developers
Classifier: License :: OSI Approved :: MIT License
Classifier: Operating System :: OS Independent
Classifier: Programming Language :: Python :: 2.7
Classifier: Programming Language :: Python :: 3.4
Classifier: Programming Language :: Python :: 3.5
Requires-Dist: requests
